autoskip/__init__.py
autoskip/__version__.py
autoskip/autoskipper.py
autoskip/cli.py
autoskip-1.0.4.dist-info/METADATA
autoskip-1.0.4.dist-info/WHEEL
autoskip-1.0.4.dist-info/entry_points.txt
autoskip-1.0.4.dist-info/top_level.txt
autoskip-1.0.4.dist-info/RECORD
