Metadata-Version: 2.1
Name: autoskip
Version: 1.0.4
Summary: Blacklist artists and songs, no login needed.
Home-page: https://github.com/Blatzar/spotify-skipper
Author: Blatzar
Author-email: blatzar@gmail.com
License: UNKNOWN
Keywords: spotify,skip
Platform: UNKNOWN
Requires-Dist: colorama
Requires-Dist: dbus-python
Requires-Dist: dbus-next
Requires-Dist: asyncio
Requires-Dist: argparse
Requires-Dist: notify-send
